[
  {
    "ContainingType": "DepartmentsController",
    "Method": "GetDepartments",
    "RelativePath": "api/Departments",
    "HttpMethod": "GET",
    "IsController": true,
    "Order": 0,
    "Parameters": [],
    "ReturnTypes": [
      {
        "Type": "System.Collections.Generic.IEnumerable\u00601[[GestionBoutiqueBack.model.Department, GestionBoutiqueBack, Version=1.0.0.0, Culture=neutral, PublicKeyToken=null]]",
        "MediaTypes": [
          "text/plain",
          "application/json",
          "text/json"
        ],
        "StatusCode": 200
      }
    ]
  },
  {
    "ContainingType": "GestionBoutiqueBack.Controllers.EmployeeDataController",
    "Method": "AddEmployee",
    "RelativePath": "api/EmployeeData",
    "HttpMethod": "POST",
    "IsController": true,
    "Order": 0,
    "Parameters": [
      {
        "Name": "employeeData",
        "Type": "GestionBoutiqueBack.model.EmployeeData",
        "IsRequired": true
      }
    ],
    "ReturnTypes": []
  },
  {
    "ContainingType": "GestionBoutiqueBack.Controllers.EmployeeDataController",
    "Method": "GetEmployees",
    "RelativePath": "api/EmployeeData",
    "HttpMethod": "GET",
    "IsController": true,
    "Order": 0,
    "Parameters": [],
    "ReturnTypes": [
      {
        "Type": "System.Collections.Generic.IEnumerable\u00601[[GestionBoutiqueBack.model.EmployeeData, GestionBoutiqueBack, Version=1.0.0.0, Culture=neutral, PublicKeyToken=null]]",
        "MediaTypes": [
          "text/plain",
          "application/json",
          "text/json"
        ],
        "StatusCode": 200
      }
    ]
  },
  {
    "ContainingType": "GestionBoutiqueBack.Controllers.EmployeeDataController",
    "Method": "GetEmployeeById",
    "RelativePath": "api/EmployeeData/{id}",
    "HttpMethod": "GET",
    "IsController": true,
    "Order": 0,
    "Parameters": [
      {
        "Name": "id",
        "Type": "System.Int32",
        "IsRequired": true
      }
    ],
    "ReturnTypes": [
      {
        "Type": "GestionBoutiqueBack.model.EmployeeData",
        "MediaTypes": [
          "text/plain",
          "application/json",
          "text/json"
        ],
        "StatusCode": 200
      }
    ]
  },
  {
    "ContainingType": "GestionBoutiqueBack.Controllers.UsersController",
    "Method": "GetAll",
    "RelativePath": "Users",
    "HttpMethod": "GET",
    "IsController": true,
    "Order": 0,
    "Parameters": [],
    "ReturnTypes": []
  },
  {
    "ContainingType": "GestionBoutiqueBack.Controllers.UsersController",
    "Method": "Authenticate",
    "RelativePath": "Users/authenticate",
    "HttpMethod": "POST",
    "IsController": true,
    "Order": 0,
    "Parameters": [
      {
        "Name": "model",
        "Type": "GestionBoutiqueBack.model.AuthenticateRequest",
        "IsRequired": true
      }
    ],
    "ReturnTypes": []
  }
]